generativemagic/__init__.py
generativemagic/arrays.py
generativemagic/deck_operations.py
generativemagic/decks.py
generativemagic/effect.py
generativemagic/guilherme.py
generativemagic/mapper.py
generativemagic/mnemonica.py
generativemagic/movement.py
generativemagic/spelling.py
generativemagic/checks/__init__.py
generativemagic/checks/basic.py
generativemagic/checks/poker.py
generativemagic/checks/searchers.py
generativemagic/checks/speller.py
generativemagic/effects/__init__.py
generativemagic/effects/aces_hand.py
generativemagic/effects/four_aces.py
generativemagic/effects/impromptu_revelation.py
generativemagic/effects/simple_effects.py
generativemagic/effects/truco_hand.py
generativemagic/effects/guilhermesilveira/__init__.py
generativemagic/effects/guilhermesilveira/matrix_square.py
generativemagic/effects/guilhermesilveira/secret_agent.py
generativemagic/effects/guilhermesilveira/spelling_position_ruler.py
generativemagic/effects/hugard_encyclopedia/__init__.py
generativemagic/effects/hugard_encyclopedia/encyclopedia.py
generativemagic/effects/hugard_encyclopedia/sagacious_joker_n1.py
generativemagic/effects/hugard_encyclopedia/simplified_reverse.py
generativemagic/effects/hugard_encyclopedia/thought_transference.py
generativemagic/effects/hugard_encyclopedia/twin_souls.py
generativemagic/history/__init__.py
generativemagic/history/effects_history.py
generativemagic/history/generic_history.py
generativemagic/history/parts.py
generativemagic/history/utils.py
generativemagic/movements/__init__.py
generativemagic/movements/faro.py
generativemagic/movements/riffle.py
generativemagic/movements/scallop.py
generativemagic/movements/simple_movements.py
generativemagic/solver/__init__.py
generativemagic/solver/rules.py
generativemagic/solver/solver.py
generativemagic/solver/variables.py
generativemagic/visualization/__init__.py
generativemagic/visualization/combinations.py
generativemagic/visualization/effect_result.py
generativemagic-0.8.0.dist-info/AUTHORS
generativemagic-0.8.0.dist-info/LICENSE
generativemagic-0.8.0.dist-info/METADATA
generativemagic-0.8.0.dist-info/WHEEL
generativemagic-0.8.0.dist-info/top_level.txt
generativemagic-0.8.0.dist-info/RECORD
