Metadata-Version: 2.1
Name: generativemagic
Version: 0.8.0
Summary: Generative magic uses computer science, mathematics, design and statistics to generate new magic.
Home-page: https://github.com/guilhermesilveira/generativemagic
Author: Guilherme Silveira
Author-email: guilherme.silveira@gmail.com
License: UNKNOWN
Platform: UNKNOWN
Classifier: Programming Language :: Python :: 3
Classifier: License :: OSI Approved :: MIT License
Classifier: Operating System :: OS Independent
Requires-Python: >=3.6
Requires-Dist: numpy (>=1.20.1)
Requires-Dist: pandas (>=1.2.3)
Requires-Dist: z3-solver (>=4.8.10)
Requires-Dist: tqdm (>=4.59)
